huggify_data/__init__.py
huggify_data/bot_modules.py
huggify_data/generate_md_modules.py
huggify_data/push_modules.py
huggify_data/scrape_modules.py
huggify_data/train_modules.py
huggify_data-0.4.4.dist-info/METADATA
huggify_data-0.4.4.dist-info/WHEEL
huggify_data-0.4.4.dist-info/RECORD
