Metadata-Version: 2.1
Name: huggify-data
Version: 0.4.4
Summary: This is a helper library to push data to HuggingFace.
Author: Yiqiao Yin
Author-email: eagle0504@gmail.com
Requires-Python: >=3.9,<3.13
Classifier: Programming Language :: Python :: 3
Classifier: Programming Language :: Python :: 3.9
Classifier: Programming Language :: Python :: 3.10
Classifier: Programming Language :: Python :: 3.11
Classifier: Programming Language :: Python :: 3.12
Requires-Dist: accelerate (>=0.20.3,<0.21.0)
Requires-Dist: bitsandbytes (==0.40.2)
Requires-Dist: datasets (==2.20.0)
Requires-Dist: huggingface-hub (==0.23.4)
Requires-Dist: matplotlib (==3.9.0)
Requires-Dist: numpy (==1.24.4)
Requires-Dist: openai (>=1.35.3,<2.0.0)
Requires-Dist: pandas (==2.2.2)
Requires-Dist: peft (==0.4.0)
Requires-Dist: pymupdf (>=1.24.5,<2.0.0)
Requires-Dist: tqdm (>=4.66.4,<5.0.0)
Requires-Dist: transformers (==4.31.0)
Requires-Dist: trl (==0.4.7)
